[{"line":1,"elements":[{"line":3,"name":"","description":"","type":"background","keyword":"Background","steps":[{"result":{"duration":628992300,"status":"passed"},"line":4,"name":"The user opens the Booking module","match":{"location":"stepdefinitions.BookingModuleDefinitions.the_user_opens_the_booking_module()"},"keyword":"Given "}]},{"start_timestamp":"2025-08-16T21:10:36.002Z","before":[{"result":{"duration":9727154500,"status":"passed"},"match":{"location":"stepdefinitions.Hooks.setUp()"}}],"line":6,"name":"Validate missing phone number","description":"","id":"validate-the-booking-module-in-the-event-management-system;validate-missing-phone-number","after":[{"result":{"duration":1347348900,"status":"passed"},"match":{"location":"stepdefinitions.Hooks.tearDown()"}}],"type":"scenario","keyword":"Scenario","steps":[{"result":{"duration":6357398100,"status":"passed"},"line":7,"name":"The user fills all required booking fields except the phone number","match":{"location":"stepdefinitions.BookingModuleDefinitions.the_user_fills_all_required_booking_fields_except_the_phone_number()"},"keyword":"When "},{"result":{"duration":279833800,"status":"passed"},"line":8,"name":"Submits the booking form","match":{"location":"stepdefinitions.BookingModuleDefinitions.submits_the_booking_form()"},"keyword":"And "},{"result":{"duration":454156200,"status":"passed"},"line":9,"name":"A phone number error message should be displayed","match":{"location":"stepdefinitions.BookingModuleDefinitions.a_phone_number_error_message_should_be_displayed()"},"keyword":"Then "}]},{"line":3,"name":"","description":"","type":"background","keyword":"Background","steps":[{"result":{"duration":427766700,"status":"passed"},"line":4,"name":"The user opens the Booking module","match":{"location":"stepdefinitions.BookingModuleDefinitions.the_user_opens_the_booking_module()"},"keyword":"Given "}]},{"start_timestamp":"2025-08-16T21:10:55.683Z","before":[{"result":{"duration":5053972200,"status":"passed"},"match":{"location":"stepdefinitions.Hooks.setUp()"}}],"line":11,"name":"Validate invalid guest count","description":"","id":"validate-the-booking-module-in-the-event-management-system;validate-invalid-guest-count","after":[{"result":{"duration":478987100,"status":"passed"},"match":{"location":"stepdefinitions.Hooks.tearDown()"}}],"type":"scenario","keyword":"Scenario","steps":[{"result":{"duration":4285244200,"status":"passed"},"line":12,"name":"The user fills the booking form with an invalid guest count","match":{"location":"stepdefinitions.BookingModuleDefinitions.the_user_fills_the_booking_form_with_an_invalid_guest_count()"},"keyword":"When "},{"result":{"duration":254669800,"status":"passed"},"line":13,"name":"Submits the booking form","match":{"location":"stepdefinitions.BookingModuleDefinitions.submits_the_booking_form()"},"keyword":"And "},{"result":{"error_message":"java.lang.AssertionError: Guest count error message is not as expected.\r\n\tat org.testng.Assert.fail(Assert.java:110)\r\n\tat stepdefinitions.BookingModuleDefinitions.a_guest_count_error_message_should_be_displayed(BookingModuleDefinitions.java:82)\r\n\tat ✽.A guest count error message should be displayed(file:///D:/EventManagementSystem/src/test/resources/features/bookingModule.feature:14)\r\n","duration":106847100,"status":"failed"},"line":14,"name":"A guest count error message should be displayed","match":{"location":"stepdefinitions.BookingModuleDefinitions.a_guest_count_error_message_should_be_displayed()"},"keyword":"Then "}]},{"line":3,"name":"","description":"","type":"background","keyword":"Background","steps":[{"result":{"duration":733639600,"status":"passed"},"line":4,"name":"The user opens the Booking module","match":{"location":"stepdefinitions.BookingModuleDefinitions.the_user_opens_the_booking_module()"},"keyword":"Given "}]},{"start_timestamp":"2025-08-16T21:11:06.376Z","before":[{"result":{"duration":3633700000,"status":"passed"},"match":{"location":"stepdefinitions.Hooks.setUp()"}}],"line":16,"name":"Validate default event type selection","description":"","id":"validate-the-booking-module-in-the-event-management-system;validate-default-event-type-selection","after":[{"result":{"duration":425252400,"status":"passed"},"match":{"location":"stepdefinitions.Hooks.tearDown()"}}],"type":"scenario","keyword":"Scenario","steps":[{"result":{"duration":3717737900,"status":"passed"},"line":17,"name":"The user fills the booking form without selecting an event type","match":{"location":"stepdefinitions.BookingModuleDefinitions.the_user_fills_the_booking_form_without_selecting_an_event_type()"},"keyword":"When "},{"result":{"duration":238449300,"status":"passed"},"line":18,"name":"Submits the booking form","match":{"location":"stepdefinitions.BookingModuleDefinitions.submits_the_booking_form()"},"keyword":"And "},{"result":{"duration":343190900,"status":"passed"},"line":19,"name":"An event type error message should be displayed","match":{"location":"stepdefinitions.BookingModuleDefinitions.an_event_type_error_message_should_be_displayed()"},"keyword":"Then "}]}],"name":"Validate the Booking module in the Event Management System","description":"","id":"validate-the-booking-module-in-the-event-management-system","keyword":"Feature","uri":"file:src/test/resources/features/bookingModule.feature","tags":[]},{"line":1,"elements":[{"line":3,"name":"","description":"","type":"background","keyword":"Background","steps":[{"result":{"duration":2670501700,"status":"passed"},"line":4,"name":"The user opens the Contact Us module","match":{"location":"stepdefinitions.ContactUsModuleDefinitions.user_opens_contactmodule()"},"keyword":"Given "}]},{"start_timestamp":"2025-08-16T21:11:15.525Z","before":[{"result":{"duration":2024301300,"status":"passed"},"match":{"location":"stepdefinitions.Hooks.setUp()"}}],"line":6,"name":"Submit with all valid fields","description":"","id":"validate-the-contact-us-module-in-the-event-management-system;submit-with-all-valid-fields","after":[{"result":{"duration":429456100,"status":"passed"},"match":{"location":"stepdefinitions.Hooks.tearDown()"}}],"type":"scenario","keyword":"Scenario","steps":[{"result":{"duration":1382117000,"status":"passed"},"line":7,"name":"The user enters valid details in all fields","match":{"location":"stepdefinitions.ContactUsModuleDefinitions.the_user_enters_valid_details_in_all_fields()"},"keyword":"When "},{"result":{"duration":237133000,"status":"passed"},"line":8,"name":"Submits the Contact Us form","match":{"location":"stepdefinitions.ContactUsModuleDefinitions.submits_the_contact_us_form()"},"keyword":"And "},{"result":{"duration":4011278500,"status":"passed"},"line":9,"name":"A success message should be displayed","match":{"location":"stepdefinitions.ContactUsModuleDefinitions.a_success_message_should_be_displayed()"},"keyword":"Then "}]},{"line":3,"name":"","description":"","type":"background","keyword":"Background","steps":[{"result":{"duration":2778156700,"status":"passed"},"line":4,"name":"The user opens the Contact Us module","match":{"location":"stepdefinitions.ContactUsModuleDefinitions.user_opens_contactmodule()"},"keyword":"Given "}]},{"start_timestamp":"2025-08-16T21:11:26.369Z","before":[{"result":{"duration":2088843500,"status":"passed"},"match":{"location":"stepdefinitions.Hooks.setUp()"}}],"line":11,"name":"Submit with invalid name","description":"","id":"validate-the-contact-us-module-in-the-event-management-system;submit-with-invalid-name","after":[{"result":{"duration":1317892500,"status":"passed"},"match":{"location":"stepdefinitions.Hooks.tearDown()"}}],"type":"scenario","keyword":"Scenario","steps":[{"result":{"duration":1412434600,"status":"passed"},"line":12,"name":"The user enters an invalid name and all other fields are valid","match":{"location":"stepdefinitions.ContactUsModuleDefinitions.the_user_enters_an_invalid_name_and_all_other_fields_are_valid()"},"keyword":"When "},{"result":{"duration":250293800,"status":"passed"},"line":13,"name":"Submits the Contact Us form","match":{"location":"stepdefinitions.ContactUsModuleDefinitions.submits_the_contact_us_form()"},"keyword":"And "},{"result":{"error_message":"java.lang.AssertionError: Name error message is not as expected.\r\n\tat org.testng.Assert.fail(Assert.java:110)\r\n\tat stepdefinitions.ContactUsModuleDefinitions.a_name_error_message_should_be_displayed(ContactUsModuleDefinitions.java:65)\r\n\tat ✽.A name error message should be displayed(file:///D:/EventManagementSystem/src/test/resources/features/contactUs.feature:14)\r\n","duration":5168419200,"status":"failed"},"line":14,"name":"A name error message should be displayed","match":{"location":"stepdefinitions.ContactUsModuleDefinitions.a_name_error_message_should_be_displayed()"},"keyword":"Then "}]},{"line":3,"name":"","description":"","type":"background","keyword":"Background","steps":[{"result":{"duration":868931000,"status":"passed"},"line":4,"name":"The user opens the Contact Us module","match":{"location":"stepdefinitions.ContactUsModuleDefinitions.user_opens_contactmodule()"},"keyword":"Given "}]},{"start_timestamp":"2025-08-16T21:11:39.455Z","before":[{"result":{"duration":4332893000,"status":"passed"},"match":{"location":"stepdefinitions.Hooks.setUp()"}}],"line":16,"name":"Submit with invalid email format","description":"","id":"validate-the-contact-us-module-in-the-event-management-system;submit-with-invalid-email-format","after":[{"result":{"duration":488884900,"status":"passed"},"match":{"location":"stepdefinitions.Hooks.tearDown()"}}],"type":"scenario","keyword":"Scenario","steps":[{"result":{"duration":1313281600,"status":"passed"},"line":17,"name":"The user enters an invalid email ID and all other fields are valid","match":{"location":"stepdefinitions.ContactUsModuleDefinitions.the_user_enters_an_invalid_email_id_and_all_other_fields_are_valid()"},"keyword":"When "},{"result":{"duration":237401200,"status":"passed"},"line":18,"name":"Submits the Contact Us form","match":{"location":"stepdefinitions.ContactUsModuleDefinitions.submits_the_contact_us_form()"},"keyword":"And "},{"result":{"error_message":"java.lang.AssertionError: Email format error message is not as expected.\r\n\tat org.testng.Assert.fail(Assert.java:110)\r\n\tat stepdefinitions.ContactUsModuleDefinitions.an_email_format_error_message_should_be_displayed(ContactUsModuleDefinitions.java:46)\r\n\tat ✽.An email format error message should be displayed(file:///D:/EventManagementSystem/src/test/resources/features/contactUs.feature:19)\r\n","duration":5169992000,"status":"failed"},"line":19,"name":"An email format error message should be displayed","match":{"location":"stepdefinitions.ContactUsModuleDefinitions.an_email_format_error_message_should_be_displayed()"},"keyword":"Then "}]}],"name":"Validate the Contact Us module in the Event Management System","description":"","id":"validate-the-contact-us-module-in-the-event-management-system","keyword":"Feature","uri":"file:src/test/resources/features/contactUs.feature","tags":[]}]